{
  "owneremail": "",
  "createdbyid": "",
  "description": "备份自动化脚本",
  "launchPoints": [],
  "createdbyemail": "",
  "interface": 0,
  "scriptlanguage": "JavaScript",
  "langcode": "ZH",
  "siteid": "",
  "action": "",
  "createdbyphone": "",
  "scheduledstatus": "",
  "variables": [],
  "comments": "",
  "autoscript": "AUTOSCRIPT.CRONTASK.BACKUP",
  "ownername": "",
  "active": 1,
  "ownerid": "",
  "version": "1.0.30",
  "orgid": "",
  "hasld": 0,
  "ibm_packagepath": "cn.shoukaiseki.tools",
  "loglevel": "ERROR",
  "ownerphone": "",
  "category": "",
  "userdefined": 1,
  "status": "Draft",
  "createdbyname": ""
}