{
  "owneremail": "",
  "createdbyid": "",
  "description": "SKS_REFLECT_TS_GENERATOR - TypeScript Definition Generator",
  "launchPoints": [],
  "createdbyemail": "",
  "interface": 0,
  "scriptlanguage": "javascript",
  "langcode": "ZH",
  "createdby": "MAXADMIN",
  "siteid": "",
  "action": "",
  "createdbyphone": "",
  "scheduledstatus": "",
  "owner": "MAXADMIN",
  "variables": [],
  "comments": "Generate TypeScript .d.ts definition from Java class via reflection",
  "autoscript": "SKS_REFLECT_TS_GENERATOR",
  "ownername": "",
  "changeby": "MAXADMIN",
  "autoscriptid": 293,
  "active": 1,
  "changedate": "2026-05-26T00:00:00+08:00",
  "ownerid": "",
  "version": "1.0.1",
  "orgid": "",
  "statusdate": "2026-05-26T00:00:00+08:00",
  "hasld": 0,
  "ibm_packagepath": "cn.shoukaiseki.tools",
  "loglevel": "ERROR",
  "ownerphone": "",
  "category": "",
  "userdefined": 1,
  "status": "Draft",
  "createdbyname": ""
}